azure_iot_hub_api/__init__.py
azure_iot_hub_api/azure_iot_hub.py
azure_iot_hub_api/models.py
azure_iot_hub_api/utilities.py
azure_iot_hub_api-0.2.2.dist-info/licenses/LICENSE
azure_iot_hub_api-0.2.2.dist-info/METADATA
azure_iot_hub_api-0.2.2.dist-info/WHEEL
azure_iot_hub_api-0.2.2.dist-info/top_level.txt
azure_iot_hub_api-0.2.2.dist-info/RECORD
