Metadata-Version: 2.4
Name: azure-iot-hub-api
Version: 0.2.2
Summary: Azure iot hub api with azure cli backend
Home-page: https://github.com/birddevelper/azure-iot-hub-api
Download-URL: https://github.com/birddevelper/azure-iot-hub-api
Author: R.E
License: GNU
Keywords: Azure,IoT,Azure IoT hub,azure cli
License-File: LICENSE
Requires-Dist: azure-cli==2.76.0
Requires-Dist: python-dateutil~=2.9
Dynamic: author
Dynamic: description
Dynamic: description-content-type
Dynamic: download-url
Dynamic: home-page
Dynamic: keywords
Dynamic: license
Dynamic: license-file
Dynamic: requires-dist
Dynamic: summary
